{"version":1,"resource":"file:///var/www/localhost/htdocs/CloudNine/Components/BaseComponent/App.jsx","entries":[{"id":"FGED.jsx","timestamp":1707214481968},{"id":"lrTA.jsx","timestamp":1707214516363},{"id":"0imJ.jsx","timestamp":1707214546656},{"id":"OYqs.jsx","timestamp":1707214565546},{"id":"blso.jsx","timestamp":1707214585504},{"id":"94fo.jsx","timestamp":1707214599238},{"id":"E17U.jsx","timestamp":1707214647414},{"id":"WhWc.jsx","timestamp":1707214682101},{"id":"39Jn.jsx","timestamp":1707215011557},{"id":"kPs0.jsx","timestamp":1707215039601},{"id":"j70V.jsx","timestamp":1707215049650},{"id":"Ti7o.jsx","timestamp":1707215078719},{"id":"sh2l.jsx","timestamp":1707215111832},{"id":"CPjv.jsx","source":"undoRedo.source","timestamp":1707215172048},{"id":"yjNx.jsx","source":"Workspace Edit","timestamp":1707215861904},{"id":"bmnd.jsx","timestamp":1707228080936},{"id":"M9Iq.jsx","timestamp":1707228620080},{"id":"sFLR.jsx","source":"Workspace Edit","timestamp":1707231087657},{"id":"Glir.jsx","source":"Workspace Edit","timestamp":1707231148329},{"id":"GKoH.jsx","timestamp":1707231226326},{"id":"1Aao.jsx","source":"undoRedo.source","timestamp":1707231241445},{"id":"ZVaf.jsx","source":"Workspace Edit","timestamp":1707231251934},{"id":"WmVP.jsx","timestamp":1707231651830},{"id":"rinZ.jsx","source":"renamed.source","timestamp":1707231706921},{"id":"yYOn.jsx","source":"moved.source","timestamp":1707231904021},{"id":"vGUD.jsx","source":"Workspace Edit","timestamp":1707231905397},{"id":"4E5E.jsx","timestamp":1707233212945},{"id":"bx5L.jsx","timestamp":1707236599512},{"id":"HOOi.jsx","timestamp":1707236611186},{"id":"CTpH.jsx","timestamp":1707237334357},{"id":"MlLJ.jsx","timestamp":1707237351719},{"id":"X0sd.jsx","timestamp":1707237383232},{"id":"1qbw.jsx","timestamp":1707237399919},{"id":"qubI.jsx","source":"undoRedo.source","timestamp":1707237415306},{"id":"LcQw.jsx","timestamp":1707281862105},{"id":"FaH4.jsx","source":"Workspace Edit","timestamp":1707281882954},{"id":"eCgx.jsx","timestamp":1707282002818},{"id":"FgEZ.jsx","source":"undoRedo.source","timestamp":1707282005784},{"id":"zebY.jsx","timestamp":1707282009327},{"id":"ANz6.jsx","source":"undoRedo.source","timestamp":1707282012724},{"id":"hW3P.jsx","timestamp":1707282018222},{"id":"Km3a.jsx","timestamp":1707296080713},{"id":"k2nP.jsx","source":"Workspace Edit","timestamp":1707296115594},{"id":"j4kd.jsx","timestamp":1707296138495},{"id":"6CL6.jsx","source":"Workspace Edit","timestamp":1707367281331},{"id":"lB4L.jsx","timestamp":1707367328752},{"id":"3s9a.jsx","timestamp":1707367342693},{"id":"aJAU.jsx","source":"Workspace Edit","timestamp":1707367445480},{"id":"d3qf.jsx","timestamp":1707367475824},{"id":"1ygx.jsx","source":"undoRedo.source","timestamp":1707367479029}]}